setup.cfg
setup.py
torsimany/__init__.py
torsimany/__main__.py
torsimany/torsimany.py
torsimany.egg-info/.DS_Store
torsimany.egg-info/PKG-INFO
torsimany.egg-info/SOURCES.txt
torsimany.egg-info/dependency_links.txt
torsimany.egg-info/entry_points.txt
torsimany.egg-info/top_level.txt