Metadata-Version: 1.1
Name: torsimany
Version: 1.0
Summary: JSON to Markdown converter - Translate any JSON file to stylish, human-readable Markdown.
Home-page: https://github.com/PolBaladas/torsimany
Author: Pol Baladas
Author-email: polbaladasluna@gmail.com
License: UNKNOWN
Download-URL: https://github.com/PolBaladas/torsimany/tarball/1.0
Keywords: markdown,json,convert
Platform: UNKNOWN
Classifier: Programming Language :: Python :: 2.7
